<genetic>
  <IDNumber>147</IDNumber>
  <shader>
    <_Outline>0.6183017267377734</_Outline>
    <_O_Width>0.8680941433558933</_O_Width>
    <_O_ColourRed>0.644543483984712</_O_ColourRed>
    <_O_ColourGreen>0.03495526220325362</_O_ColourGreen>
    <_O_ColourBlue>0.8923380022862779</_O_ColourBlue>
  </shader>
  <shader>
    <_Cel>0.9550181118958802</_Cel>
    <_C_Levels>0.605840021173301</_C_Levels>
    <_C_ColourRed>0.6481735158690466</_C_ColourRed>
    <_C_ColourGreen>0.8971488129504478</_C_ColourGreen>
    <_C_ColourBlue>0.0861703011809497</_C_ColourBlue>
  </shader>
  <shader>
    <_Hatching>0.45812769051025515</_Hatching>
    <_H_Intensity>0.35700027283918867</_H_Intensity>
    <_H_ColourRed>0.9574282346005676</_H_ColourRed>
    <_H_ColourGreen>0.7569415254833441</_H_ColourGreen>
    <_H_ColourBlue>0.9849908246163985</_H_ColourBlue>
  </shader>
</genetic>